{"storage_initialized":1,"field_definitions":{"access_level":{"v_options":["anon","visitor","member","staff","admin"],"options":["*anon","visitor","member","staff","admin"],"default":"anon","label":"Access Level","validate_as":"enum","description":"Permission level for feature access","must_validate":1,"required":1,"max_length":20,"type":"enum","null_value":"","field_name":"access_level"},"user_status":{"must_validate":1,"description":"Account status for access control","max_length":20,"type":"enum","required":1,"field_name":"user_status","null_value":"","options":["*Eligible","OK","Inactive"],"default":"Eligible","v_options":["Eligible","OK","Inactive"],"label":"User Status","validate_as":"enum"},"prefix":{"field_name":"prefix","max_length":10,"type":"enum","description":"Name prefix or title","must_validate":0,"null_value":"","required":0,"validate_as":"enum","label":"Prefix","v_options":["","Dr","Mr","Ms","Mrs","Mx","Prof","Hon","Sir","Madam"],"default":"","options":["*","Dr","Mr","Ms","Mrs","Mx","Prof","Hon","Sir","Madam"]},"user_id":{"field_name":"user_id","null_value":"","type":"system","max_length":30,"required":1,"must_validate":0,"description":"User login ID - Primary authentication identifier","label":"User ID","options":[],"default":""},"last_name":{"validate_as":"name","default":"","options":[],"label":"Last Name","null_value":"","field_name":"last_name","description":"User's last name","must_validate":1,"required":0,"type":"text","max_length":50},"term_ends":{"null_value":"0000-00-00","field_name":"term_ends","required":0,"max_length":10,"type":"date","description":"Account expiration date (YYYY-MM-DD)","must_validate":0,"validate_as":"date","label":"Term Ends","default":"","options":[]},"first_name":{"options":[],"default":"","label":"First Name","validate_as":"name","description":"User's first name","must_validate":1,"required":0,"type":"text","max_length":50,"null_value":"","field_name":"first_name"},"moniker":{"default":"","options":[],"label":"Moniker","validate_as":"moniker","required":1,"null_value":"","description":"User's preferred display name, nickname, or initials","must_validate":1,"max_length":24,"type":"text","field_name":"moniker"},"created_date":{"field_name":"created_date","null_value":"0000-00-00 00:00:00","must_validate":0,"description":"Timestamp when user account was created","max_length":19,"type":"system","required":1,"default":"0000-00-00 00:00:00","options":[],"label":"Created Date"},"last_login_date":{"field_name":"last_login_date","null_value":"0000-00-00 00:00:00","must_validate":0,"description":"Timestamp of last successful login","type":"timestamp","max_length":19,"required":0,"validate_as":"timestamp","options":[],"default":"0000-00-00 00:00:00","label":"Last Login Date"},"phone":{"null_value":"","field_name":"phone","description":"Phone number with country code","must_validate":0,"required":0,"max_length":20,"type":"phone","validate_as":"phone","options":[],"default":"","label":"Phone"},"middle_name":{"field_name":"middle_name","must_validate":1,"description":"User's middle name","max_length":50,"type":"text","validate_as":"name","default":"","options":[],"label":"Middle Name","null_value":"","required":0},"email":{"options":[],"default":"","label":"Email","validate_as":"email","must_validate":0,"description":"Email address for notifications","type":"email","max_length":255,"required":0,"field_name":"email","null_value":""},"last_mod_date":{"field_name":"last_mod_date","null_value":"0000-00-00 00:00:00","max_length":19,"type":"system","required":0,"must_validate":0,"description":"Timestamp of last profile modification","label":"Last Modification Date","options":[],"default":"0000-00-00 00:00:00"},"title":{"must_validate":0,"description":"User's position or job title","max_length":100,"type":"text","required":0,"field_name":"title","null_value":"","default":"","options":[],"label":"Title","validate_as":"text"},"organization":{"validate_as":"text","options":[],"default":"","label":"Organization","field_name":"organization","null_value":"","must_validate":0,"description":"User's organization or affiliation","type":"text","max_length":100,"required":0},"suffix":{"label":"Suffix","v_options":["","Jr","Sr","II","III","IV","V","PhD","MD","DDS","Esq"],"default":"","options":["*","Jr","Sr","II","III","IV","V","PhD","MD","DDS","Esq"],"validate_as":"enum","required":0,"type":"enum","max_length":10,"description":"Name suffix or professional designation","must_validate":0,"null_value":"","field_name":"suffix"},"text_ok":{"options":[],"default":"","label":"Text OK","validate_as":"boolean","must_validate":0,"description":"Consent for text messages (1=yes, 0=no)","max_length":1,"type":"boolean","required":0,"field_name":"text_ok","null_value":0}},"backend_config":{"fields":["user_id","moniker","user_status","access_level","first_name","middle_name","last_name","prefix","suffix","organization","title","email","phone","text_ok","last_login_date","term_ends","last_mod_date","created_date"],"storage_dir":"./desk","db_full_path":"./desk/users.db","db_file":"users.db","field_definitions":{"access_level":{"v_options":["anon","visitor","member","staff","admin"],"options":["*anon","visitor","member","staff","admin"],"default":"anon","label":"Access Level","validate_as":"enum","description":"Permission level for feature access","must_validate":1,"required":1,"max_length":20,"type":"enum","null_value":"","field_name":"access_level"},"user_status":{"must_validate":1,"description":"Account status for access control","max_length":20,"type":"enum","required":1,"field_name":"user_status","null_value":"","options":["*Eligible","OK","Inactive"],"default":"Eligible","v_options":["Eligible","OK","Inactive"],"label":"User Status","validate_as":"enum"},"prefix":{"field_name":"prefix","max_length":10,"type":"enum","description":"Name prefix or title","must_validate":0,"null_value":"","required":0,"validate_as":"enum","label":"Prefix","v_options":["","Dr","Mr","Ms","Mrs","Mx","Prof","Hon","Sir","Madam"],"default":"","options":["*","Dr","Mr","Ms","Mrs","Mx","Prof","Hon","Sir","Madam"]},"user_id":{"field_name":"user_id","null_value":"","type":"system","max_length":30,"required":1,"must_validate":0,"description":"User login ID - Primary authentication identifier","label":"User ID","options":[],"default":""},"last_name":{"validate_as":"name","default":"","options":[],"label":"Last Name","null_value":"","field_name":"last_name","description":"User's last name","must_validate":1,"required":0,"type":"text","max_length":50},"term_ends":{"null_value":"0000-00-00","field_name":"term_ends","required":0,"max_length":10,"type":"date","description":"Account expiration date (YYYY-MM-DD)","must_validate":0,"validate_as":"date","label":"Term Ends","default":"","options":[]},"first_name":{"options":[],"default":"","label":"First Name","validate_as":"name","description":"User's first name","must_validate":1,"required":0,"type":"text","max_length":50,"null_value":"","field_name":"first_name"},"moniker":{"default":"","options":[],"label":"Moniker","validate_as":"moniker","required":1,"null_value":"","description":"User's preferred display name, nickname, or initials","must_validate":1,"max_length":24,"type":"text","field_name":"moniker"},"created_date":{"field_name":"created_date","null_value":"0000-00-00 00:00:00","must_validate":0,"description":"Timestamp when user account was created","max_length":19,"type":"system","required":1,"default":"0000-00-00 00:00:00","options":[],"label":"Created Date"},"last_login_date":{"field_name":"last_login_date","null_value":"0000-00-00 00:00:00","must_validate":0,"description":"Timestamp of last successful login","type":"timestamp","max_length":19,"required":0,"validate_as":"timestamp","options":[],"default":"0000-00-00 00:00:00","label":"Last Login Date"},"phone":{"null_value":"","field_name":"phone","description":"Phone number with country code","must_validate":0,"required":0,"max_length":20,"type":"phone","validate_as":"phone","options":[],"default":"","label":"Phone"},"middle_name":{"field_name":"middle_name","must_validate":1,"description":"User's middle name","max_length":50,"type":"text","validate_as":"name","default":"","options":[],"label":"Middle Name","null_value":"","required":0},"email":{"options":[],"default":"","label":"Email","validate_as":"email","must_validate":0,"description":"Email address for notifications","type":"email","max_length":255,"required":0,"field_name":"email","null_value":""},"last_mod_date":{"field_name":"last_mod_date","null_value":"0000-00-00 00:00:00","max_length":19,"type":"system","required":0,"must_validate":0,"description":"Timestamp of last profile modification","label":"Last Modification Date","options":[],"default":"0000-00-00 00:00:00"},"title":{"must_validate":0,"description":"User's position or job title","max_length":100,"type":"text","required":0,"field_name":"title","null_value":"","default":"","options":[],"label":"Title","validate_as":"text"},"organization":{"validate_as":"text","options":[],"default":"","label":"Organization","field_name":"organization","null_value":"","must_validate":0,"description":"User's organization or affiliation","type":"text","max_length":100,"required":0},"suffix":{"label":"Suffix","v_options":["","Jr","Sr","II","III","IV","V","PhD","MD","DDS","Esq"],"default":"","options":["*","Jr","Sr","II","III","IV","V","PhD","MD","DDS","Esq"],"validate_as":"enum","required":0,"type":"enum","max_length":10,"description":"Name suffix or professional designation","must_validate":0,"null_value":"","field_name":"suffix"},"text_ok":{"options":[],"default":"","label":"Text OK","validate_as":"boolean","must_validate":0,"description":"Consent for text messages (1=yes, 0=no)","max_length":1,"type":"boolean","required":0,"field_name":"text_ok","null_value":0}},"table_name":"users"},"generated":"2026-02-08 01:42:13","fields":["user_id","moniker","user_status","access_level","first_name","middle_name","last_name","prefix","suffix","organization","title","email","phone","text_ok","last_login_date","term_ends","last_mod_date","created_date"],"backend_module":"Concierge::Users::Database","version":"v0.7.0"}